{
  "model_id": "volvo-xc60-b5-bensin",
  "calculated_at": "2026-04-28T23:14:22.468751+00:00",
  "assumptions": {
    "mileage_per_year": 1500,
    "ownership_years": 4,
    "fuel_price_kr_per_liter": 18.5,
    "electricity_price_kr_per_kwh": 1.5
  },
  "result": {
    "total_cost": 478057,
    "monthly_cost": 9960,
    "cost_per_mil": 80,
    "breakdown": {
      "depreciation": 336793,
      "fuel": 83250,
      "tax": 3024,
      "insurance": {
        "low": 19200,
        "high": 32400,
        "estimate": 24800
      },
      "service": 22500,
      "tires": 7200,
      "besiktning": 490
    },
    "depreciation_curve": [
      {
        "year": 0,
        "value": 718000,
        "confidence": "fixed",
        "data_points": 0
      },
      {
        "year": 1,
        "value": 583482,
        "confidence": "medium",
        "data_points": 140
      },
      {
        "year": 2,
        "value": 483507,
        "confidence": "medium",
        "data_points": 225
      },
      {
        "year": 3,
        "value": 401946,
        "confidence": "medium",
        "data_points": 250
      },
      {
        "year": 4,
        "value": 381207,
        "confidence": "medium",
        "data_points": 222
      },
      {
        "year": 5,
        "value": 344978,
        "confidence": "medium",
        "data_points": 250
      },
      {
        "year": 6,
        "value": 325407,
        "confidence": "medium",
        "data_points": 242
      },
      {
        "year": 7,
        "value": 297507,
        "confidence": "medium",
        "data_points": 195
      },
      {
        "year": 8,
        "value": 278907,
        "confidence": "medium",
        "data_points": 177
      },
      {
        "year": 9,
        "value": 245438,
        "confidence": "estimated",
        "data_points": 0
      }
    ]
  },
  "confidence": "high",
  "data_quality_notes": []
}