{
  "model_id": "polestar-2-lr",
  "scraped_at": "2026-06-15T12:07:02.595451+00:00",
  "source": "autouncle",
  "price_type": "estimated_transaction",
  "asking_price_discount": 0.93,
  "years": {
    "2025": {
      "median_price": 547770,
      "count": 4,
      "total_on_page": 46,
      "price_type": "estimated_transaction",
      "min_price": 525450,
      "max_price": 693780,
      "median_mileage_mil": 20252
    },
    "2024": {
      "median_price": 516057,
      "count": 3,
      "total_on_page": 25,
      "price_type": "estimated_transaction",
      "min_price": 514197,
      "max_price": 516057,
      "median_mileage_mil": 20247
    },
    "2023": {
      "median_price": 399807,
      "count": 6,
      "total_on_page": 70,
      "price_type": "estimated_transaction",
      "p5_price": 324570,
      "p95_price": 427521,
      "min_price": 324570,
      "max_price": 427521
    },
    "2022": {
      "median_price": 302157,
      "count": 3,
      "total_on_page": 46,
      "price_type": "estimated_transaction",
      "min_price": 259470,
      "max_price": 371907
    },
    "2021": {
      "median_price": 313782,
      "count": 4,
      "total_on_page": 33,
      "price_type": "estimated_transaction",
      "min_price": 287370,
      "max_price": 367257
    },
    "2020": {
      "median_price": 319827,
      "count": 5,
      "total_on_page": 31,
      "price_type": "estimated_transaction",
      "p5_price": 287370,
      "p95_price": 344007,
      "min_price": 287370,
      "max_price": 344007
    }
  },
  "validation": {
    "is_monotonic": false,
    "min_count_per_year": 3,
    "confidence": "low"
  }
}